foundation/__init__.py
foundation/urls.py
foundation/static/foundation/css/.fontcustom-data
foundation/static/foundation/css/foundation-icons.css
foundation/static/foundation/css/foundation-icons.eot
foundation/static/foundation/css/foundation-icons.ttf
foundation/static/foundation/css/foundation-icons.woff
foundation/static/foundation/css/foundation.css
foundation/static/foundation/css/foundation.min.css
foundation/static/foundation/js/vendor/foundation.js
foundation/static/foundation/js/vendor/foundation.min.js
foundation/static/foundation/js/vendor/jquery.js
foundation/static/foundation/js/vendor/what-input.js
foundation/static/foundation/svg/foundation-icons.svg
foundation/static/foundation/svg/svgs/fi-address-book.svg
foundation/static/foundation/svg/svgs/fi-alert.svg
foundation/static/foundation/svg/svgs/fi-align-center.svg
foundation/static/foundation/svg/svgs/fi-align-justify.svg
foundation/static/foundation/svg/svgs/fi-align-left.svg
foundation/static/foundation/svg/svgs/fi-align-right.svg
foundation/static/foundation/svg/svgs/fi-anchor.svg
foundation/static/foundation/svg/svgs/fi-annotate.svg
foundation/static/foundation/svg/svgs/fi-archive.svg
foundation/static/foundation/svg/svgs/fi-arrow-down.svg
foundation/static/foundation/svg/svgs/fi-arrow-left.svg
foundation/static/foundation/svg/svgs/fi-arrow-right.svg
foundation/static/foundation/svg/svgs/fi-arrow-up.svg
foundation/static/foundation/svg/svgs/fi-arrows-compress.svg
foundation/static/foundation/svg/svgs/fi-arrows-expand.svg
foundation/static/foundation/svg/svgs/fi-arrows-in.svg
foundation/static/foundation/svg/svgs/fi-arrows-out.svg
foundation/static/foundation/svg/svgs/fi-asl.svg
foundation/static/foundation/svg/svgs/fi-asterisk.svg
foundation/static/foundation/svg/svgs/fi-at-sign.svg
foundation/static/foundation/svg/svgs/fi-background-color.svg
foundation/static/foundation/svg/svgs/fi-battery-empty.svg
foundation/static/foundation/svg/svgs/fi-battery-full.svg
django_zurb_foundation_6-6.7.4.dist-info/LICENSE
django_zurb_foundation_6-6.7.4.dist-info/METADATA
django_zurb_foundation_6-6.7.4.dist-info/WHEEL
django_zurb_foundation_6-6.7.4.dist-info/top_level.txt
django_zurb_foundation_6-6.7.4.dist-info/RECORD
