Metadata-Version: 2.1
Name: django-zurb-foundation-6
Version: 6.7.4
Summary: Django Zurb Foundation package for Django 4.
Home-page: https://github.com/jlbyh2o/django-zurb-foundation-6
Author: Jeremy Bywater
Author-email: nougats-dance0b@icloud.com
License: Unlicense
Platform: UNKNOWN
Classifier: Environment :: Web Environment
Classifier: Framework :: Django :: 4
Classifier: Intended Audience :: Developers
Classifier: Natural Language :: English
Classifier: License :: OSI Approved :: The Unlicense (Unlicense)
Classifier: Operating System :: OS Independent
Classifier: Programming Language :: Python :: 3
Classifier: Development Status :: 4 - Beta
Classifier: Topic :: Utilities
Requires-Python: >3.6
License-File: LICENSE
